{
    "index_patterns":
    [
        "t_asset_information"
    ],
    "aliases":
    {},
    "mappings":
    {
        "dynamic": "true",
        "dynamic_templates":
        [
            {
                "keyword_fields":
                {
                    "mapping":
                    {
                        "type": "keyword"
                    },
                    "match": "keyword_*"
                }
            },
            {
                "text_fields":
                {
                    "mapping":
                    {
                        "analyzer": "mmseg_simple",
                        "type": "text"
                    },
                    "match": "text_*"
                }
            },
            {
                "integer_fields":
                {
                    "mapping":
                    {
                        "type": "integer"
                    },
                    "match": "integer_*"
                }
            },
            {
                "long_fields":
                {
                    "mapping":
                    {
                        "type": "long"
                    },
                    "match": "long_*"
                }
            },
            {
                "float_fields":
                {
                    "mapping":
                    {
                        "type": "float"
                    },
                    "match": "float_*"
                }
            },
            {
                "timestamp_fields":
                {
                    "mapping":
                    {
                        "format": "yyyy-MM-dd HH:mm:ss||strict_date_optional_time||epoch_millis",
                        "type": "date"
                    },
                    "match": "timestamp_*"
                }
            },
            {
                "double_fields":
                {
                    "mapping":
                    {
                        "type": "double"
                    },
                    "match": "float_*"
                }
            },
            {
                "boolean_fields":
                {
                    "mapping":
                    {
                        "type": "boolean"
                    },
                    "match": "boolean_*"
                }
            },
            {
                "stat_fields":
                {
                    "mapping":
                    {
                        "type": "double"
                    },
                    "match": "stat_*"
                }
            }
        ],
        "properties":
        {
            "assetId":
            {
                "ignore_above": 8191,
                "type": "keyword"
            },
            "assetName":
            {
                "ignore_above": 8191,
                "type": "keyword"
            },
            "assetImportance":
            {
                "ignore_above": 8191,
                "type": "keyword"
            },
            "assetLabel":
            {
                "ignore_above": 8191,
                "type": "keyword"
            },
            "assetType":
            {
                "ignore_above": 8191,
                "type": "keyword"
            },
            "orgId":
            {
                "ignore_above": 8191,
                "type": "keyword"
            },
            "netId":
            {
                "ignore_above": 8191,
                "type": "keyword"
            },
            "assetOwner":
            {
                "ignore_above": 8191,
                "type": "keyword"
            },
            "assetSourceModel":
            {
                "ignore_above": 8191,
                "type": "keyword"
            },
            "assetSource":
            {
                "ignore_above": 8191,
                "type": "keyword"
            },
            "edrAssetSource":
            {
                "ignore_above": 8191,
                "type": "keyword"
            },
            "edrId":
            {
                "ignore_above": 8191,
                "type": "keyword"
            },
            "assetNumber":
            {
                "ignore_above": 8191,
                "type": "keyword"
            },
            "assetUseState":
            {
                "ignore_above": 8191,
                "type": "keyword"
            },
            "assetUser":
            {
                "ignore_above": 8191,
                "type": "keyword"
            },
            "assetConfidentiality":
            {
                "ignore_above": 8191,
                "type": "keyword"
            },
            "assetIntegrity":
            {
                "ignore_above": 8191,
                "type": "keyword"
            },
            "assetUsability":
            {
                "ignore_above": 8191,
                "type": "keyword"
            },
            "assetLevelProtection":
            {
                "type": "boolean"
            },
            "assetLocalization":
            {
                "type": "boolean"
            },
            "assetIot":
            {
                "type": "boolean"
            },
            "assetIdc":
            {
                "ignore_above": 8191,
                "type": "keyword"
            },
            "assetGeoRegion":
            {
                "ignore_above": 8191,
                "type": "keyword"
            },
            "assetGeoDetailedAddress":
            {
                "ignore_above": 8191,
                "type": "keyword"
            },
            "assetDescribe":
            {
                "ignore_above": 8191,
                "type": "keyword"
            },
            "osType":
            {
                "ignore_above": 8191,
                "type": "keyword"
            },
            "osVersion":
            {
                "ignore_above": 8191,
                "type": "keyword"
            },
            "os":
            {
                "ignore_above": 8191,
                "type": "keyword"
            },
            "kernelVersion":
            {
                "ignore_above": 8191,
                "type": "keyword"
            },
            "cpuInfo":
            {
                "ignore_above": 8191,
                "type": "keyword"
            },
            "memoryInfo":
            {
                "ignore_above": 8191,
                "type": "keyword"
            },
            "hdInfo":
            {
                "ignore_above": 8191,
                "type": "keyword"
            },
            "gpuInfo":
            {
                "ignore_above": 8191,
                "type": "keyword"
            },
            "deviceFactory":
            {
                "ignore_above": 8191,
                "type": "keyword"
            },
            "deviceModel":
            {
                "ignore_above": 8191,
                "type": "keyword"
            },
            "deviceVersion":
            {
                "ignore_above": 8191,
                "type": "keyword"
            },
            "assetRegion":
            {
                "ignore_above": 8191,
                "type": "keyword"
            },
            "assetManagementEnable":
            {
                "type": "boolean"
            },
            "assetManagementAddress":
            {
                "ignore_above": 8191,
                "type": "keyword"
            },
            "assetOnlineMonitor":
            {
                "type": "boolean"
            },
            "assetOnlineMonitorType":
            {
                "ignore_above": 8191,
                "type": "keyword"
            },
            "assetOnlineMonitorCycle":
            {
                "ignore_above": 8191,
                "type": "keyword"
            },
            "confirm":
            {
                "type": "boolean"
            },
            "fromSubordinatePlatform":
            {
                "type": "boolean"
            },
            "platformCodes":
            {
                "ignore_above": 8191,
                "type": "keyword"
            },
            "updateTime":
            {
                "type": "date",
                "format": "yyyy-MM-dd HH:mm:ss||strict_date_optional_time||epoch_millis"
            },
            "createTime":
            {
                "type": "date",
                "format": "yyyy-MM-dd HH:mm:ss||strict_date_optional_time||epoch_millis"
            },
            "warehouseTime":
            {
                "type": "date",
                "format": "yyyy-MM-dd HH:mm:ss||strict_date_optional_time||epoch_millis"
            },
            "fieldSource":
            {
                "type": "nested"
            },
            "extraField":
            {
                "type": "nested"
            },
            "assetIdentifications":
            {
                "properties":
                {
                    "id":
                    {
                        "ignore_above": 8191,
                        "type": "keyword"
                    },
                    "assetId":
                    {
                        "ignore_above": 8191,
                        "type": "keyword"
                    },
                    "netId":
                    {
                        "ignore_above": 8191,
                        "type": "keyword"
                    },
                    "formatType":
                    {
                        "ignore_above": 8191,
                        "type": "keyword"
                    },
                    "identificationType":
                    {
                        "ignore_above": 8191,
                        "type": "keyword"
                    },
                    "identification":
                    {
                        "ignore_above": 8191,
                        "type": "keyword"
                    },
                    "ipHex":
                    {
                        "ignore_above": 8191,
                        "type": "keyword"
                    },
                    "ipType":
                    {
                        "ignore_above": 8191,
                        "type": "keyword"
                    },
                    "order":
                    {
                        "type": "long"
                    }
                }
            },
            "relationContacts":
            {
                "properties":
                {
                    "id":
                    {
                        "ignore_above": 8191,
                        "type": "keyword"
                    },
                    "relationType":
                    {
                        "ignore_above": 8191,
                        "type": "keyword"
                    },
                    "relationId":
                    {
                        "ignore_above": 8191,
                        "type": "keyword"
                    },
                    "contactName":
                    {
                        "ignore_above": 8191,
                        "type": "keyword"
                    },
                    "contactTelephone":
                    {
                        "ignore_above": 8191,
                        "type": "keyword"
                    },
                    "contactEmail":
                    {
                        "ignore_above": 8191,
                        "type": "keyword"
                    },
                    "order":
                    {
                        "type": "long"
                    }
                }
            },
            "assetStatisticalResult":
            {
                "properties":
                {
                    "assetId":
                    {
                        "ignore_above": 8191,
                        "type": "keyword"
                    },
                    "lastUpTime":
                    {
                        "type": "date",
                        "format": "yyyy-MM-dd HH:mm:ss||strict_date_optional_time||epoch_millis"
                    },
                    "assetState":
                    {
                        "ignore_above": 8191,
                        "type": "keyword"
                    },
                    "assetHighVulnerabilities":
                    {
                        "type": "long"
                    },
                    "assetMediumVulnerabilities":
                    {
                        "type": "long"
                    },
                    "assetLowVulnerabilities":
                    {
                        "type": "long"
                    },
                    "sevenDaysHighAlarm":
                    {
                        "type": "long"
                    },
                    "sevenDaysMediumAlarm":
                    {
                        "type": "long"
                    },
                    "sevenDaysLowAlarm":
                    {
                        "type": "long"
                    },
                    "todayLogNum":
                    {
                        "type": "long"
                    },
                    "edrProtectionState":
                    {
                        "ignore_above": 8191,
                        "type": "keyword"
                    },
                    "versionObject":
                    {
                        "ignore_above": 8191,
                        "type": "keyword"
                    },
                    "updateTime":
                    {
                        "type": "date",
                        "format": "yyyy-MM-dd HH:mm:ss||strict_date_optional_time||epoch_millis"
                    },
                    "createTime":
                    {
                        "type": "date",
                        "format": "yyyy-MM-dd HH:mm:ss||strict_date_optional_time||epoch_millis"
                    }
                }
            },
            "assetRating":
            {
                "properties":
                {
                    "id":
                    {
                        "ignore_above": 8191,
                        "type": "keyword"
                    },
                    "assetId":
                    {
                        "ignore_above": 8191,
                        "type": "keyword"
                    },
                    "assetHealthState":
                    {
                        "ignore_above": 8191,
                        "type": "keyword"
                    },
                    "assetScore":
                    {
                        "type": "float"
                    },
                    "tags":
                    {
                        "ignore_above": 8191,
                        "type": "keyword"
                    },
                    "rateGroup":
                    {
                        "ignore_above": 8191,
                        "type": "keyword"
                    },
                    "fromSubordinatePlatform":
                    {
                        "type": "boolean"
                    },
                    "ratingTime":
                    {
                        "type": "date",
                        "format": "yyyy-MM-dd HH:mm:ss||strict_date_optional_time||epoch_millis"
                    },
                    "createTime":
                    {
                        "type": "date",
                        "format": "yyyy-MM-dd HH:mm:ss||strict_date_optional_time||epoch_millis"
                    }
                }
            },
            "assetSolidifiedLabel":
            {
                "properties":
                {
                    "device":
                    {
                        "ignore_above": 8191,
                        "type": "keyword"
                    },
                    "linkageDeviceStatus":
                    {
                        "ignore_above": 8191,
                        "type": "keyword"
                    },
                    "isWebSystem":
                    {
                        "type": "boolean"
                    },
                    "probe":
                    {
                        "ignore_above": 8191,
                        "type": "keyword"
                    },
                    "datasource":
                    {
                        "ignore_above": 8191,
                        "type": "keyword"
                    },
                    "createTime":
                    {
                        "type": "date",
                        "format": "yyyy-MM-dd HH:mm:ss||strict_date_optional_time||epoch_millis"
                    },
                    "updateTime":
                    {
                        "type": "date",
                        "format": "yyyy-MM-dd HH:mm:ss||strict_date_optional_time||epoch_millis"
                    }
                }
            },
            "assetSoftware":
            {
                "properties":
                {
                    "id":
                    {
                        "ignore_above": 8191,
                        "type": "keyword"
                    },
                    "assetId":
                    {
                        "ignore_above": 8191,
                        "type": "keyword"
                    },
                    "name":
                    {
                        "ignore_above": 8191,
                        "type": "keyword"
                    },
                    "publisher":
                    {
                        "ignore_above": 8191,
                        "type": "keyword"
                    },
                    "version":
                    {
                        "ignore_above": 8191,
                        "type": "keyword"
                    },
                    "installPath":
                    {
                        "ignore_above": 8191,
                        "type": "keyword"
                    },
                    "updateTime":
                    {
                        "type": "date",
                        "format": "yyyy-MM-dd HH:mm:ss||strict_date_optional_time||epoch_millis"
                    },
                    "createTime":
                    {
                        "type": "date",
                        "format": "yyyy-MM-dd HH:mm:ss||strict_date_optional_time||epoch_millis"
                    }
                }
            },
            "assetAccounts":
            {
                "properties":
                {
                    "id":
                    {
                        "ignore_above": 8191,
                        "type": "keyword"
                    },
                    "assetId":
                    {
                        "ignore_above": 8191,
                        "type": "keyword"
                    },
                    "userName":
                    {
                        "ignore_above": 8191,
                        "type": "keyword"
                    },
                    "root":
                    {
                        "type": "boolean"
                    },
                    "gid":
                    {
                        "ignore_above": 8191,
                        "type": "keyword"
                    },
                    "status":
                    {
                        "ignore_above": 8191,
                        "type": "keyword"
                    },
                    "passwordExpire":
                    {
                        "type": "date",
                        "format": "yyyy-MM-dd HH:mm:ss||strict_date_optional_time||epoch_millis"
                    },
                    "logonType":
                    {
                        "ignore_above": 8191,
                        "type": "keyword"
                    },
                    "lastLogonTime":
                    {
                        "type": "date",
                        "format": "yyyy-MM-dd HH:mm:ss||strict_date_optional_time||epoch_millis"
                    },
                    "updateTime":
                    {
                        "type": "date",
                        "format": "yyyy-MM-dd HH:mm:ss||strict_date_optional_time||epoch_millis"
                    },
                    "createTime":
                    {
                        "type": "date",
                        "format": "yyyy-MM-dd HH:mm:ss||strict_date_optional_time||epoch_millis"
                    }
                }
            },
            "assetProcesses":
            {
                "properties":
                {
                    "id":
                    {
                        "ignore_above": 8191,
                        "type": "keyword"
                    },
                    "assetId":
                    {
                        "ignore_above": 8191,
                        "type": "keyword"
                    },
                    "name":
                    {
                        "ignore_above": 8191,
                        "type": "keyword"
                    },
                    "path":
                    {
                        "ignore_above": 8191,
                        "type": "keyword"
                    },
                    "memUsed":
                    {
                        "ignore_above": 8191,
                        "type": "keyword"
                    },
                    "cpuUsed":
                    {
                        "ignore_above": 8191,
                        "type": "keyword"
                    },
                    "commandLine":
                    {
                        "ignore_above": 8191,
                        "type": "keyword"
                    },
                    "userName":
                    {
                        "ignore_above": 8191,
                        "type": "keyword"
                    },
                    "pname":
                    {
                        "ignore_above": 8191,
                        "type": "keyword"
                    },
                    "startTime":
                    {
                        "type": "date",
                        "format": "yyyy-MM-dd HH:mm:ss||strict_date_optional_time||epoch_millis"
                    },
                    "updateTime":
                    {
                        "type": "date",
                        "format": "yyyy-MM-dd HH:mm:ss||strict_date_optional_time||epoch_millis"
                    },
                    "createTime":
                    {
                        "type": "date",
                        "format": "yyyy-MM-dd HH:mm:ss||strict_date_optional_time||epoch_millis"
                    }
                }
            },
            "assetPorts":
            {
                "properties":
                {
                    "id":
                    {
                        "ignore_above": 8191,
                        "type": "keyword"
                    },
                    "assetId":
                    {
                        "ignore_above": 8191,
                        "type": "keyword"
                    },
                    "assetIp":
                    {
                        "ignore_above": 8191,
                        "type": "keyword"
                    },
                    "port":
                    {
                        "ignore_above": 8191,
                        "type": "keyword"
                    },
                    "protocol":
                    {
                        "ignore_above": 8191,
                        "type": "keyword"
                    },
                    "serviceName":
                    {
                        "ignore_above": 8191,
                        "type": "keyword"
                    },
                    "serverVersion":
                    {
                        "ignore_above": 8191,
                        "type": "keyword"
                    },
                    "status":
                    {
                        "ignore_above": 8191,
                        "type": "keyword"
                    },
                    "message":
                    {
                        "ignore_above": 8191,
                        "type": "keyword"
                    },
                    "source":
                    {
                        "ignore_above": 8191,
                        "type": "keyword"
                    },
                    "fingerprintName":
                    {
                        "ignore_above": 8191,
                        "type": "keyword"
                    },
                    "fingerprintClass2":
                    {
                        "ignore_above": 8191,
                        "type": "keyword"
                    },
                    "vendorName":
                    {
                        "ignore_above": 8191,
                        "type": "keyword"
                    },
                    "tag":
                    {
                        "ignore_above": 8191,
                        "type": "keyword"
                    },
                    "fingerprintVersion":
                    {
                        "ignore_above": 8191,
                        "type": "keyword"
                    },
                    "findTime":
                    {
                        "type": "date",
                        "format": "yyyy-MM-dd HH:mm:ss||strict_date_optional_time||epoch_millis"
                    },
                    "updateTime":
                    {
                        "type": "date",
                        "format": "yyyy-MM-dd HH:mm:ss||strict_date_optional_time||epoch_millis"
                    },
                    "createTime":
                    {
                        "type": "date",
                        "format": "yyyy-MM-dd HH:mm:ss||strict_date_optional_time||epoch_millis"
                    }
                }
            },
            "_meta":
            {
                "type": "nested"
            }
        }
    },
    "order": 0,
    "settings":
    {
        "index":
        {
            "indexing":
            {
                "slowlog":
                {
                    "level": "info",
                    "threshold":
                    {
                        "index":
                        {
                            "info": "5s"
                        }
                    }
                }
            },
            "lifecycle":
            {
                "name": "common-policy-shard-1",
                "rollover_alias": "ailpha-securitylog-flow-20230512"
            },
            "mapping":
            {
                "ignore_malformed": "true"
            },
            "merge":
            {
                "policy":
                {
                    "floor_segment": "10mb",
                    "max_merge_at_once": "30",
                    "max_merged_segment": "1gb",
                    "segments_per_tier": "60"
                },
                "scheduler":
                {
                    "auto_throttle": "true",
                    "max_merge_count": "100",
                    "max_thread_count": "1"
                }
            },
            "number_of_replicas": "0",
            "number_of_shards": "1",
            "refresh_interval": "60s",
            "search":
            {
                "slowlog":
                {
                    "level": "info",
                    "threshold":
                    {
                        "fetch":
                        {
                            "info": "5s"
                        },
                        "query":
                        {
                            "info": "10s"
                        }
                    }
                }
            },
            "translog":
            {
                "durability": "async",
                "flush_threshold_size": "1024mb",
                "generation_threshold_size": "128mb",
                "retention":
                {
                    "age": "1h",
                    "size": "32mb"
                }
            },
            "unassigned":
            {
                "node_left":
                {
                    "delayed_timeout": "10m"
                }
            }
        }
    }
}